[
    {
        "id": 54518,
        "nombre": "PAMPLONA"
    },
    {
        "id": 54874,
        "nombre": "VILLA DEL ROSARIO"
    },
    {
        "id": 11001,
        "nombre": "BOGOTA"
    },
    {
        "id": 54,
        "nombre": "NORTE DE SANTANDER"
    },
    {
        "id": 47,
        "nombre": "MAGDALENA"
    },
    {
        "id": 25,
        "nombre": "CUNDINAMARCA"
    },
    {
        "id": 54001,
        "nombre": "CUCUTA"
    },
    {
        "id": 20,
        "nombre": "CESAR"
    },
    {
        "id": 68,
        "nombre": "SANTANDER"
    },
    {
        "id": 15,
        "nombre": "BOYACA"
    },
    {
        "id": 44,
        "nombre": "GUAJIRA"
    },
    {
        "id": 85,
        "nombre": "CASANARE"
    },
    {
        "id": 95,
        "nombre": "SAN JOSE DEL GUAVIARE"
    }
]